[
    {
        "aula1": "teste1",
        "aula2": "teste2",
        "aula3": "teste3",
        "aula4": "teste4",
        "": ""
    },
    {
        "aula1": null,
        "aula2": null,
        "aula3": "",
        "aula4": "",
        "": ""
    },
    {
        "aula1": null,
        "aula2": null,
        "aula3": "",
        "aula4": "",
        "": ""
    },
    {
        "aula1": "",
        "aula2": "",
        "aula3": "",
        "aula4": "",
        "": ""
    },
    {
        "aula1": "",
        "aula2": "",
        "aula3": "",
        "aula4": "",
        "": ""
    },
    {
        "aula1": "",
        "aula2": "",
        "aula3": "",
        "aula4": "",
        "": ""
    },
    {
        "aula1": "",
        "aula2": "",
        "aula3": "",
        "aula4": "",
        "": ""
    },
    {
        "aula1": "",
        "aula2": "",
        "aula3": "",
        "aula4": "",
        "": ""
    },
    {
        "aula1": "",
        "aula2": "",
        "aula3": "",
        "aula4": "",
        "": ""
    }
]